examples/client_example.py
examples/server_example.py
superbot/__init__.py
superbot/bots/__init__.py
superbot/bots/base_bot.py
superbot/bots/dual_piper.py
superbot/sensors/__init__.py
superbot/sensors/base_sensor.py
superbot/sensors/cams/__init__.py
superbot/sensors/cams/cam_orbe.py
superbot/sensors/cams/cam_rs.py
superbot/sensors/cams/utils.py
superbot/stabilization/__init__.py
superbot/stabilization/realtime_chunking.py
superbot/transport/__init__.py
superbot/transport/client.py
superbot/transport/server.py
superbot/transport/local/__init__.py
superbot/transport/local/client.py
superbot/transport/local/memfd_mmap_transport.py
superbot/transport/local/server.py
superbot/transport/remote/__init__.py
superbot/transport/remote/client.py
superbot/transport/remote/server.py
superbot/utils/__init__.py
superbot/utils/rotation.py
tests/piper_ctrl_gripper.py
tests/piper_ctrl_joint.py
tests/piper_read_joint_state.py
tests/piper_set_gripper_zero.py
superbot2-0.1.1.dist-info/METADATA
superbot2-0.1.1.dist-info/WHEEL
superbot2-0.1.1.dist-info/top_level.txt
superbot2-0.1.1.dist-info/RECORD
