Metadata-Version: 2.4
Name: superbot2
Version: 0.1.1
Summary: A modular robotics framework for controlling various robots
Author-email: SuperBot Team <team@superbot.com>
License: MIT
Project-URL: Homepage, https://github.com/superbot/superbot
Project-URL: Repository, https://github.com/superbot/superbot.git
Project-URL: Documentation, https://superbot.readthedocs.io/
Classifier: Development Status :: 3 - Alpha
Classifier: Intended Audience :: Developers
Classifier: License :: OSI Approved :: MIT License
Classifier: Programming Language :: Python :: 3
Classifier: Programming Language :: Python :: 3.8
Classifier: Programming Language :: Python :: 3.9
Classifier: Programming Language :: Python :: 3.10
Classifier: Programming Language :: Python :: 3.11
Classifier: Programming Language :: Python :: 3.12
Classifier: Programming Language :: Python :: 3.13
Requires-Dist: numpy>=1.21.0
Requires-Dist: scipy>=1.7.0
Requires-Dist: PyYAML>=6.0
Requires-Dist: pyzmq>=25.0.0
Requires-Dist: pyrealsense2; sys_platform == "linux"
Requires-Dist: pyorbbecsdk2; sys_platform == "linux"
Provides-Extra: dev
Requires-Dist: pytest>=6.0; extra == "dev"
Requires-Dist: black>=22.0; extra == "dev"
Requires-Dist: flake8>=4.0; extra == "dev"
Requires-Dist: mypy>=0.950; extra == "dev"
Provides-Extra: docs
Requires-Dist: sphinx>=4.0; extra == "docs"
Requires-Dist: sphinx-rtd-theme>=1.0; extra == "docs"
